parsbale.py
parsbale-1.1.0.dist-info/METADATA
parsbale-1.1.0.dist-info/WHEEL
parsbale-1.1.0.dist-info/top_level.txt
parsbale-1.1.0.dist-info/RECORD
