Metadata-Version: 2.4
Name: parsbale
Version: 1.1.0
Author-email: abasjy <raiagpt3@gmail.com>
License: MIT
Project-URL: Homepage, https://github.com/abasjy
Classifier: Programming Language :: Python :: 3
Classifier: Programming Language :: Python :: 3.8
Classifier: Programming Language :: Python :: 3.9
Classifier: Programming Language :: Python :: 3.10
Classifier: Programming Language :: Python :: 3.11
Classifier: Development Status :: 3 - Alpha
Classifier: License :: OSI Approved :: MIT License
Classifier: Operating System :: OS Independent
Requires-Python: >=3.8
